petprep_extract_tacs/__init__.py
petprep_extract_tacs/extract_tacs.py
petprep_extract_tacs/interfaces/__init__.py
petprep_extract_tacs/interfaces/fs_model.py
petprep_extract_tacs/interfaces/fs_preprocess.py
petprep_extract_tacs/interfaces/petsurfer.py
petprep_extract_tacs/interfaces/segment.py
petprep_extract_tacs/parcellations/lh.HCPMMP1.annot
petprep_extract_tacs/parcellations/rh.HCPMMP1.annot
petprep_extract_tacs/utils/__init__.py
petprep_extract_tacs/utils/datasink.py
petprep_extract_tacs/utils/merge_tacs.py
petprep_extract_tacs/utils/pet.py
petprep_extract_tacs/utils/raphe+pons.ctab
petprep_extract_tacs/utils/raphe+pons.n21.d114.h5
petprep_extract_tacs/utils/raphe+pons_cleaned.ctab
petprep_extract_tacs/utils/sclimbic.ctab
petprep_extract_tacs/utils/sclimbic_cleaned.ctab
petprep_extract_tacs/utils/utils.py
petprep_extract_tacs-0.0.6.dist-info/METADATA
petprep_extract_tacs-0.0.6.dist-info/WHEEL
petprep_extract_tacs-0.0.6.dist-info/entry_points.txt
petprep_extract_tacs-0.0.6.dist-info/licenses/LICENSE
petprep_extract_tacs-0.0.6.dist-info/RECORD
