Metadata-Version: 2.4
Name: petprep_extract_tacs
Version: 0.0.6
Summary: PETPrep Extract Time Activity Curves Workflow
License: MIT
License-File: LICENSE
Author: Martin Norgaard
Author-email: martin.noergaard@di.ku.dk
Requires-Python: >=3.9,<4.0
Classifier: Development Status :: 3 - Alpha
Classifier: Intended Audience :: Developers
Classifier: License :: OSI Approved :: MIT License
Classifier: Programming Language :: Python :: 3
Classifier: Programming Language :: Python :: 3.9
Classifier: Programming Language :: Python :: 3.10
Classifier: Programming Language :: Python :: 3.11
Classifier: Programming Language :: Python :: 3.12
Classifier: Programming Language :: Python :: 3.13
Classifier: Programming Language :: Python :: 3.14
Requires-Dist: astor (==0.8.1)
Requires-Dist: bids (==0.0)
Requires-Dist: bids-validator (==1.11.0)
Requires-Dist: click (==8.1.3)
Requires-Dist: contourpy (==1.0.7)
Requires-Dist: docopt (==0.6.2)
Requires-Dist: formulaic (==0.5.2)
Requires-Dist: interface-meta (==1.3.0)
Requires-Dist: ipython (==8.13.2)
Requires-Dist: matplotlib (==3.7.1)
Requires-Dist: networkx (==3.1)
Requires-Dist: nibabel (==5.1.0)
Requires-Dist: nipype (==1.8.6)
Requires-Dist: niworkflows (==1.10.2)
Requires-Dist: num2words (==0.5.12)
Requires-Dist: numpy (==1.26.4)
Requires-Dist: pandas (==2.0.0)
Requires-Dist: patsy (==0.5.3)
Requires-Dist: petutils (>=0.1.0,<0.2.0)
Requires-Dist: pillow (==9.5.0)
Requires-Dist: pybids (>=0.16.1)
Requires-Dist: rdflib (==6.3.2)
Requires-Dist: scipy (>=1.3)
Requires-Dist: seaborn (==0.12.2)
Requires-Dist: sqlalchemy (==1.3.24)
Requires-Dist: statsmodels (==0.13.5)
Requires-Dist: traits (==6.3.2)
Requires-Dist: wrapt (==1.15.0)
Project-URL: Homepage, https://github.com/mnoergaard/petprep_extract_tacs
